{"id":"base5","name":"Team Rocket","series":"Base","release_date":"2000/04/24","total":83,"cards":[{"id":"base5-1","n":"1","name":"Dark Alakazam","rarity":"Rare Holo","img":"https://images.pokemontcg.io/base5/1.png","large":"https://images.pokemontcg.io/base5/1_hires.png","types":["Psychic"],"supertype":"Pok\u00e9mon"},{"id":"base5-2","n":"2","name":"Dark Arbok","rarity":"Rare Holo","img":"https://images.pokemontcg.io/base5/2.png","large":"https://images.pokemontcg.io/base5/2_hires.png","types":["Grass"],"supertype":"Pok\u00e9mon"},{"id":"base5-3","n":"3","name":"Dark Blastoise","rarity":"Rare Holo","img":"https://images.pokemontcg.io/base5/3.png","large":"https://images.pokemontcg.io/base5/3_hires.png","types":["Water"],"supertype":"Pok\u00e9mon"},{"id":"base5-4","n":"4","name":"Dark Charizard","rarity":"Rare Holo","img":"https://images.pokemontcg.io/base5/4.png","large":"https://images.pokemontcg.io/base5/4_hires.png","types":["Fire"],"supertype":"Pok\u00e9mon"},{"id":"base5-5","n":"5","name":"Dark Dragonite","rarity":"Rare Holo","img":"https://images.pokemontcg.io/base5/5.png","large":"https://images.pokemontcg.io/base5/5_hires.png","types":["Colorless"],"supertype":"Pok\u00e9mon"},{"id":"base5-6","n":"6","name":"Dark Dugtrio","rarity":"Rare Holo","img":"https://images.pokemontcg.io/base5/6.png","large":"https://images.pokemontcg.io/base5/6_hires.png","types":["Fighting"],"supertype":"Pok\u00e9mon"},{"id":"base5-7","n":"7","name":"Dark Golbat","rarity":"Rare Holo","img":"https://images.pokemontcg.io/base5/7.png","large":"https://images.pokemontcg.io/base5/7_hires.png","types":["Grass"],"supertype":"Pok\u00e9mon"},{"id":"base5-8","n":"8","name":"Dark Gyarados","rarity":"Rare Holo","img":"https://images.pokemontcg.io/base5/8.png","large":"https://images.pokemontcg.io/base5/8_hires.png","types":["Water"],"supertype":"Pok\u00e9mon"},{"id":"base5-9","n":"9","name":"Dark Hypno","rarity":"Rare Holo","img":"https://images.pokemontcg.io/base5/9.png","large":"https://images.pokemontcg.io/base5/9_hires.png","types":["Psychic"],"supertype":"Pok\u00e9mon"},{"id":"base5-10","n":"10","name":"Dark Machamp","rarity":"Rare Holo","img":"https://images.pokemontcg.io/base5/10.png","large":"https://images.pokemontcg.io/base5/10_hires.png","types":["Fighting"],"supertype":"Pok\u00e9mon"},{"id":"base5-11","n":"11","name":"Dark Magneton","rarity":"Rare Holo","img":"https://images.pokemontcg.io/base5/11.png","large":"https://images.pokemontcg.io/base5/11_hires.png","types":["Lightning"],"supertype":"Pok\u00e9mon"},{"id":"base5-12","n":"12","name":"Dark Slowbro","rarity":"Rare Holo","img":"https://images.pokemontcg.io/base5/12.png","large":"https://images.pokemontcg.io/base5/12_hires.png","types":["Psychic"],"supertype":"Pok\u00e9mon"},{"id":"base5-13","n":"13","name":"Dark Vileplume","rarity":"Rare Holo","img":"https://images.pokemontcg.io/base5/13.png","large":"https://images.pokemontcg.io/base5/13_hires.png","types":["Grass"],"supertype":"Pok\u00e9mon"},{"id":"base5-14","n":"14","name":"Dark Weezing","rarity":"Rare Holo","img":"https://images.pokemontcg.io/base5/14.png","large":"https://images.pokemontcg.io/base5/14_hires.png","types":["Grass"],"supertype":"Pok\u00e9mon"},{"id":"base5-15","n":"15","name":"Here Comes Team Rocket!","rarity":"Rare Holo","img":"https://images.pokemontcg.io/base5/15.png","large":"https://images.pokemontcg.io/base5/15_hires.png","types":[],"supertype":"Trainer"},{"id":"base5-16","n":"16","name":"Rocket's Sneak Attack","rarity":"Rare Holo","img":"https://images.pokemontcg.io/base5/16.png","large":"https://images.pokemontcg.io/base5/16_hires.png","types":[],"supertype":"Trainer"},{"id":"base5-17","n":"17","name":"Rainbow Energy","rarity":"Rare Holo","img":"https://images.pokemontcg.io/base5/17.png","large":"https://images.pokemontcg.io/base5/17_hires.png","types":[],"supertype":"Energy"},{"id":"base5-18","n":"18","name":"Dark Alakazam","rarity":"Rare","img":"https://images.pokemontcg.io/base5/18.png","large":"https://images.pokemontcg.io/base5/18_hires.png","types":["Psychic"],"supertype":"Pok\u00e9mon"},{"id":"base5-19","n":"19","name":"Dark Arbok","rarity":"Rare","img":"https://images.pokemontcg.io/base5/19.png","large":"https://images.pokemontcg.io/base5/19_hires.png","types":["Grass"],"supertype":"Pok\u00e9mon"},{"id":"base5-20","n":"20","name":"Dark Blastoise","rarity":"Rare","img":"https://images.pokemontcg.io/base5/20.png","large":"https://images.pokemontcg.io/base5/20_hires.png","types":["Water"],"supertype":"Pok\u00e9mon"},{"id":"base5-21","n":"21","name":"Dark Charizard","rarity":"Rare","img":"https://images.pokemontcg.io/base5/21.png","large":"https://images.pokemontcg.io/base5/21_hires.png","types":["Fire"],"supertype":"Pok\u00e9mon"},{"id":"base5-22","n":"22","name":"Dark Dragonite","rarity":"Rare","img":"https://images.pokemontcg.io/base5/22.png","large":"https://images.pokemontcg.io/base5/22_hires.png","types":["Colorless"],"supertype":"Pok\u00e9mon"},{"id":"base5-23","n":"23","name":"Dark Dugtrio","rarity":"Rare","img":"https://images.pokemontcg.io/base5/23.png","large":"https://images.pokemontcg.io/base5/23_hires.png","types":["Fighting"],"supertype":"Pok\u00e9mon"},{"id":"base5-24","n":"24","name":"Dark Golbat","rarity":"Rare","img":"https://images.pokemontcg.io/base5/24.png","large":"https://images.pokemontcg.io/base5/24_hires.png","types":["Grass"],"supertype":"Pok\u00e9mon"},{"id":"base5-25","n":"25","name":"Dark Gyarados","rarity":"Rare","img":"https://images.pokemontcg.io/base5/25.png","large":"https://images.pokemontcg.io/base5/25_hires.png","types":["Water"],"supertype":"Pok\u00e9mon"},{"id":"base5-26","n":"26","name":"Dark Hypno","rarity":"Rare","img":"https://images.pokemontcg.io/base5/26.png","large":"https://images.pokemontcg.io/base5/26_hires.png","types":["Psychic"],"supertype":"Pok\u00e9mon"},{"id":"base5-27","n":"27","name":"Dark Machamp","rarity":"Rare","img":"https://images.pokemontcg.io/base5/27.png","large":"https://images.pokemontcg.io/base5/27_hires.png","types":["Fighting"],"supertype":"Pok\u00e9mon"},{"id":"base5-28","n":"28","name":"Dark Magneton","rarity":"Rare","img":"https://images.pokemontcg.io/base5/28.png","large":"https://images.pokemontcg.io/base5/28_hires.png","types":["Lightning"],"supertype":"Pok\u00e9mon"},{"id":"base5-29","n":"29","name":"Dark Slowbro","rarity":"Rare","img":"https://images.pokemontcg.io/base5/29.png","large":"https://images.pokemontcg.io/base5/29_hires.png","types":["Psychic"],"supertype":"Pok\u00e9mon"},{"id":"base5-30","n":"30","name":"Dark Vileplume","rarity":"Rare","img":"https://images.pokemontcg.io/base5/30.png","large":"https://images.pokemontcg.io/base5/30_hires.png","types":["Grass"],"supertype":"Pok\u00e9mon"},{"id":"base5-31","n":"31","name":"Dark Weezing","rarity":"Rare","img":"https://images.pokemontcg.io/base5/31.png","large":"https://images.pokemontcg.io/base5/31_hires.png","types":["Grass"],"supertype":"Pok\u00e9mon"},{"id":"base5-32","n":"32","name":"Dark Charmeleon","rarity":"Uncommon","img":"https://images.pokemontcg.io/base5/32.png","large":"https://images.pokemontcg.io/base5/32_hires.png","types":["Fire"],"supertype":"Pok\u00e9mon"},{"id":"base5-33","n":"33","name":"Dark Dragonair","rarity":"Uncommon","img":"https://images.pokemontcg.io/base5/33.png","large":"https://images.pokemontcg.io/base5/33_hires.png","types":["Colorless"],"supertype":"Pok\u00e9mon"},{"id":"base5-34","n":"34","name":"Dark Electrode","rarity":"Uncommon","img":"https://images.pokemontcg.io/base5/34.png","large":"https://images.pokemontcg.io/base5/34_hires.png","types":["Lightning"],"supertype":"Pok\u00e9mon"},{"id":"base5-35","n":"35","name":"Dark Flareon","rarity":"Uncommon","img":"https://images.pokemontcg.io/base5/35.png","large":"https://images.pokemontcg.io/base5/35_hires.png","types":["Fire"],"supertype":"Pok\u00e9mon"},{"id":"base5-36","n":"36","name":"Dark Gloom","rarity":"Uncommon","img":"https://images.pokemontcg.io/base5/36.png","large":"https://images.pokemontcg.io/base5/36_hires.png","types":["Grass"],"supertype":"Pok\u00e9mon"},{"id":"base5-37","n":"37","name":"Dark Golduck","rarity":"Uncommon","img":"https://images.pokemontcg.io/base5/37.png","large":"https://images.pokemontcg.io/base5/37_hires.png","types":["Water"],"supertype":"Pok\u00e9mon"},{"id":"base5-38","n":"38","name":"Dark Jolteon","rarity":"Uncommon","img":"https://images.pokemontcg.io/base5/38.png","large":"https://images.pokemontcg.io/base5/38_hires.png","types":["Lightning"],"supertype":"Pok\u00e9mon"},{"id":"base5-39","n":"39","name":"Dark Kadabra","rarity":"Uncommon","img":"https://images.pokemontcg.io/base5/39.png","large":"https://images.pokemontcg.io/base5/39_hires.png","types":["Psychic"],"supertype":"Pok\u00e9mon"},{"id":"base5-40","n":"40","name":"Dark Machoke","rarity":"Uncommon","img":"https://images.pokemontcg.io/base5/40.png","large":"https://images.pokemontcg.io/base5/40_hires.png","types":["Fighting"],"supertype":"Pok\u00e9mon"},{"id":"base5-41","n":"41","name":"Dark Muk","rarity":"Uncommon","img":"https://images.pokemontcg.io/base5/41.png","large":"https://images.pokemontcg.io/base5/41_hires.png","types":["Grass"],"supertype":"Pok\u00e9mon"},{"id":"base5-42","n":"42","name":"Dark Persian","rarity":"Uncommon","img":"https://images.pokemontcg.io/base5/42.png","large":"https://images.pokemontcg.io/base5/42_hires.png","types":["Colorless"],"supertype":"Pok\u00e9mon"},{"id":"base5-43","n":"43","name":"Dark Primeape","rarity":"Uncommon","img":"https://images.pokemontcg.io/base5/43.png","large":"https://images.pokemontcg.io/base5/43_hires.png","types":["Fighting"],"supertype":"Pok\u00e9mon"},{"id":"base5-44","n":"44","name":"Dark Rapidash","rarity":"Uncommon","img":"https://images.pokemontcg.io/base5/44.png","large":"https://images.pokemontcg.io/base5/44_hires.png","types":["Fire"],"supertype":"Pok\u00e9mon"},{"id":"base5-45","n":"45","name":"Dark Vaporeon","rarity":"Uncommon","img":"https://images.pokemontcg.io/base5/45.png","large":"https://images.pokemontcg.io/base5/45_hires.png","types":["Water"],"supertype":"Pok\u00e9mon"},{"id":"base5-46","n":"46","name":"Dark Wartortle","rarity":"Uncommon","img":"https://images.pokemontcg.io/base5/46.png","large":"https://images.pokemontcg.io/base5/46_hires.png","types":["Water"],"supertype":"Pok\u00e9mon"},{"id":"base5-47","n":"47","name":"Magikarp","rarity":"Uncommon","img":"https://images.pokemontcg.io/base5/47.png","large":"https://images.pokemontcg.io/base5/47_hires.png","types":["Water"],"supertype":"Pok\u00e9mon"},{"id":"base5-48","n":"48","name":"Porygon","rarity":"Uncommon","img":"https://images.pokemontcg.io/base5/48.png","large":"https://images.pokemontcg.io/base5/48_hires.png","types":["Colorless"],"supertype":"Pok\u00e9mon"},{"id":"base5-49","n":"49","name":"Abra","rarity":"Common","img":"https://images.pokemontcg.io/base5/49.png","large":"https://images.pokemontcg.io/base5/49_hires.png","types":["Psychic"],"supertype":"Pok\u00e9mon"},{"id":"base5-50","n":"50","name":"Charmander","rarity":"Common","img":"https://images.pokemontcg.io/base5/50.png","large":"https://images.pokemontcg.io/base5/50_hires.png","types":["Fire"],"supertype":"Pok\u00e9mon"},{"id":"base5-51","n":"51","name":"Dark Raticate","rarity":"Common","img":"https://images.pokemontcg.io/base5/51.png","large":"https://images.pokemontcg.io/base5/51_hires.png","types":["Colorless"],"supertype":"Pok\u00e9mon"},{"id":"base5-52","n":"52","name":"Diglett","rarity":"Common","img":"https://images.pokemontcg.io/base5/52.png","large":"https://images.pokemontcg.io/base5/52_hires.png","types":["Fighting"],"supertype":"Pok\u00e9mon"},{"id":"base5-53","n":"53","name":"Dratini","rarity":"Common","img":"https://images.pokemontcg.io/base5/53.png","large":"https://images.pokemontcg.io/base5/53_hires.png","types":["Colorless"],"supertype":"Pok\u00e9mon"},{"id":"base5-54","n":"54","name":"Drowzee","rarity":"Common","img":"https://images.pokemontcg.io/base5/54.png","large":"https://images.pokemontcg.io/base5/54_hires.png","types":["Psychic"],"supertype":"Pok\u00e9mon"},{"id":"base5-55","n":"55","name":"Eevee","rarity":"Common","img":"https://images.pokemontcg.io/base5/55.png","large":"https://images.pokemontcg.io/base5/55_hires.png","types":["Colorless"],"supertype":"Pok\u00e9mon"},{"id":"base5-56","n":"56","name":"Ekans","rarity":"Common","img":"https://images.pokemontcg.io/base5/56.png","large":"https://images.pokemontcg.io/base5/56_hires.png","types":["Grass"],"supertype":"Pok\u00e9mon"},{"id":"base5-57","n":"57","name":"Grimer","rarity":"Common","img":"https://images.pokemontcg.io/base5/57.png","large":"https://images.pokemontcg.io/base5/57_hires.png","types":["Grass"],"supertype":"Pok\u00e9mon"},{"id":"base5-58","n":"58","name":"Koffing","rarity":"Common","img":"https://images.pokemontcg.io/base5/58.png","large":"https://images.pokemontcg.io/base5/58_hires.png","types":["Grass"],"supertype":"Pok\u00e9mon"},{"id":"base5-59","n":"59","name":"Machop","rarity":"Common","img":"https://images.pokemontcg.io/base5/59.png","large":"https://images.pokemontcg.io/base5/59_hires.png","types":["Fighting"],"supertype":"Pok\u00e9mon"},{"id":"base5-60","n":"60","name":"Magnemite","rarity":"Common","img":"https://images.pokemontcg.io/base5/60.png","large":"https://images.pokemontcg.io/base5/60_hires.png","types":["Lightning"],"supertype":"Pok\u00e9mon"},{"id":"base5-61","n":"61","name":"Mankey","rarity":"Common","img":"https://images.pokemontcg.io/base5/61.png","large":"https://images.pokemontcg.io/base5/61_hires.png","types":["Fighting"],"supertype":"Pok\u00e9mon"},{"id":"base5-62","n":"62","name":"Meowth","rarity":"Common","img":"https://images.pokemontcg.io/base5/62.png","large":"https://images.pokemontcg.io/base5/62_hires.png","types":["Colorless"],"supertype":"Pok\u00e9mon"},{"id":"base5-63","n":"63","name":"Oddish","rarity":"Common","img":"https://images.pokemontcg.io/base5/63.png","large":"https://images.pokemontcg.io/base5/63_hires.png","types":["Grass"],"supertype":"Pok\u00e9mon"},{"id":"base5-64","n":"64","name":"Ponyta","rarity":"Common","img":"https://images.pokemontcg.io/base5/64.png","large":"https://images.pokemontcg.io/base5/64_hires.png","types":["Fire"],"supertype":"Pok\u00e9mon"},{"id":"base5-65","n":"65","name":"Psyduck","rarity":"Common","img":"https://images.pokemontcg.io/base5/65.png","large":"https://images.pokemontcg.io/base5/65_hires.png","types":["Water"],"supertype":"Pok\u00e9mon"},{"id":"base5-66","n":"66","name":"Rattata","rarity":"Common","img":"https://images.pokemontcg.io/base5/66.png","large":"https://images.pokemontcg.io/base5/66_hires.png","types":["Colorless"],"supertype":"Pok\u00e9mon"},{"id":"base5-67","n":"67","name":"Slowpoke","rarity":"Common","img":"https://images.pokemontcg.io/base5/67.png","large":"https://images.pokemontcg.io/base5/67_hires.png","types":["Psychic"],"supertype":"Pok\u00e9mon"},{"id":"base5-68","n":"68","name":"Squirtle","rarity":"Common","img":"https://images.pokemontcg.io/base5/68.png","large":"https://images.pokemontcg.io/base5/68_hires.png","types":["Water"],"supertype":"Pok\u00e9mon"},{"id":"base5-69","n":"69","name":"Voltorb","rarity":"Common","img":"https://images.pokemontcg.io/base5/69.png","large":"https://images.pokemontcg.io/base5/69_hires.png","types":["Lightning"],"supertype":"Pok\u00e9mon"},{"id":"base5-70","n":"70","name":"Zubat","rarity":"Common","img":"https://images.pokemontcg.io/base5/70.png","large":"https://images.pokemontcg.io/base5/70_hires.png","types":["Grass"],"supertype":"Pok\u00e9mon"},{"id":"base5-71","n":"71","name":"Here Comes Team Rocket!","rarity":"Rare","img":"https://images.pokemontcg.io/base5/71.png","large":"https://images.pokemontcg.io/base5/71_hires.png","types":[],"supertype":"Trainer"},{"id":"base5-72","n":"72","name":"Rocket's Sneak Attack","rarity":"Rare","img":"https://images.pokemontcg.io/base5/72.png","large":"https://images.pokemontcg.io/base5/72_hires.png","types":[],"supertype":"Trainer"},{"id":"base5-73","n":"73","name":"The Boss's Way","rarity":"Uncommon","img":"https://images.pokemontcg.io/base5/73.png","large":"https://images.pokemontcg.io/base5/73_hires.png","types":[],"supertype":"Trainer"},{"id":"base5-74","n":"74","name":"Challenge!","rarity":"Uncommon","img":"https://images.pokemontcg.io/base5/74.png","large":"https://images.pokemontcg.io/base5/74_hires.png","types":[],"supertype":"Trainer"},{"id":"base5-75","n":"75","name":"Digger","rarity":"Uncommon","img":"https://images.pokemontcg.io/base5/75.png","large":"https://images.pokemontcg.io/base5/75_hires.png","types":[],"supertype":"Trainer"},{"id":"base5-76","n":"76","name":"Imposter Oak's Revenge","rarity":"Uncommon","img":"https://images.pokemontcg.io/base5/76.png","large":"https://images.pokemontcg.io/base5/76_hires.png","types":[],"supertype":"Trainer"},{"id":"base5-77","n":"77","name":"Nightly Garbage Run","rarity":"Uncommon","img":"https://images.pokemontcg.io/base5/77.png","large":"https://images.pokemontcg.io/base5/77_hires.png","types":[],"supertype":"Trainer"},{"id":"base5-78","n":"78","name":"Goop Gas Attack","rarity":"Common","img":"https://images.pokemontcg.io/base5/78.png","large":"https://images.pokemontcg.io/base5/78_hires.png","types":[],"supertype":"Trainer"},{"id":"base5-79","n":"79","name":"Sleep!","rarity":"Common","img":"https://images.pokemontcg.io/base5/79.png","large":"https://images.pokemontcg.io/base5/79_hires.png","types":[],"supertype":"Trainer"},{"id":"base5-80","n":"80","name":"Rainbow Energy","rarity":"Rare","img":"https://images.pokemontcg.io/base5/80.png","large":"https://images.pokemontcg.io/base5/80_hires.png","types":[],"supertype":"Energy"},{"id":"base5-81","n":"81","name":"Full Heal Energy","rarity":"Uncommon","img":"https://images.pokemontcg.io/base5/81.png","large":"https://images.pokemontcg.io/base5/81_hires.png","types":[],"supertype":"Energy"},{"id":"base5-82","n":"82","name":"Potion Energy","rarity":"Uncommon","img":"https://images.pokemontcg.io/base5/82.png","large":"https://images.pokemontcg.io/base5/82_hires.png","types":[],"supertype":"Energy"},{"id":"base5-83","n":"83","name":"Dark Raichu","rarity":"Rare Secret","img":"https://images.pokemontcg.io/base5/83.png","large":"https://images.pokemontcg.io/base5/83_hires.png","types":["Lightning"],"supertype":"Pok\u00e9mon"}]}